tasks/asvspoof_task.py
tasks/clotho_task.py
tasks/crema_d_task.py
tasks/desed_task.py
tasks/esc50_task.py
tasks/finger_snap_task.py
tasks/fluentspeechcommands_kws_task.py
tasks/freemusicarchive_genre_task.py
tasks/fsd50k_task.py
tasks/fsdkaggle2018_task.py
tasks/gtzan_task.py
tasks/inside_outside_car_task.py
tasks/key_scratching_task.py
tasks/libricount_task.py
tasks/librispeech_asr_task.py
tasks/librispeech_male_female_task.py
tasks/liveenv_task.py
tasks/maestro_task.py
tasks/nsynth_instument_task.py
tasks/ravdess_task.py
tasks/speechcommandsv1_task.py
tasks/subway_broadcast_task.py
tasks/urbansound8k_task.py
tasks/vocalimitations_task.py
tasks/vocalsound_task.py
tasks/voxceleb1_task.py
tasks/voxlingua33_task.py
xares/audio_encoder_checker.py
xares/audiowebdataset.py
xares/common.py
xares/metrics.py
xares/run.py
xares/task.py
xares/trainer.py
xares/utils.py
xares/models/asr.py
xares/models/retrival.py
xares/models/simple.py
xares-0.1.3.dist-info/licenses/LICENSE
xares-0.1.3.dist-info/METADATA
xares-0.1.3.dist-info/WHEEL
xares-0.1.3.dist-info/top_level.txt
xares-0.1.3.dist-info/RECORD
