Metadata-Version: 2.4
Name: xares
Version: 0.1.3
Summary: eXtensive Audio Representation and Evaluation Suite
Author-email: Junbo Zhang <zhangjunbo1@xiaomi.com>, Heinrich Dinkel <dinkelheinrich@xiaomi.com>, Yadong Niu <niuyadong@xiaomi.com>, Jiahao Zhou <zhoujiahao5@xiaomi.com>, Chenyu Liu <liuchenyu3@xiaomi.com>
License:                                  Apache License
Project-URL: Repository, https://github.com/jimbozhang/xares.git
Requires-Python: >=3.10
License-File: LICENSE
Requires-Dist: loguru
Requires-Dist: numpy
Requires-Dist: jiwer
Requires-Dist: scikit-learn>=1.6.0
Requires-Dist: torch>=2.2.1
Requires-Dist: torchaudio>=2.2.1
Requires-Dist: torchmetrics>=1.6.1
Requires-Dist: pandas>=2.2.3
Requires-Dist: pytorch-ignite>=0.5.1
Requires-Dist: soundfile>=0.13.1
Requires-Dist: transformers>=4.47.1
Requires-Dist: tqdm
Requires-Dist: webdataset>=0.2.100
Provides-Extra: examples
Requires-Dist: dasheng; extra == "examples"
Dynamic: license-file
